mynotiontools/NotionHelper.py
mynotiontools/__init__.py
mynotiontools/__version__.py
mynotiontools/core.py
mynotiontools/main.py
mynotiontools-0.1.2.dist-info/LICENSE
mynotiontools-0.1.2.dist-info/METADATA
mynotiontools-0.1.2.dist-info/WHEEL
mynotiontools-0.1.2.dist-info/top_level.txt
mynotiontools-0.1.2.dist-info/RECORD
