Metadata-Version: 2.1
Name: mynotiontools
Version: 0.1.2
Summary: Some tools for notion, Just for fun.
Home-page: https://github.com/suyelu/mynotion
Author: Vincent Su
Author-email: suyelu@hotmail.com
License: MIT
Platform: UNKNOWN
Classifier: License :: OSI Approved :: MIT License
Classifier: Programming Language :: Python
Classifier: Programming Language :: Python :: 3
Classifier: Programming Language :: Python :: 3.6
Classifier: Programming Language :: Python :: Implementation :: CPython
Classifier: Programming Language :: Python :: Implementation :: PyPy
Requires-Python: >=3.6.0
License-File: LICENSE
